{
  "parent": "minecraft:recipes/root",
  "criteria": {
    "has_sermium": {
      "conditions": {
        "items": [
          {
            "items": [
              "taloi:sermium"
            ]
          }
        ]
      },
      "trigger": "minecraft:inventory_changed"
    },
    "has_the_recipe": {
      "conditions": {
        "recipe": "taloi:sermium_core"
      },
      "trigger": "minecraft:recipe_unlocked"
    }
  },
  "requirements": [
    [
      "has_sermium",
      "has_the_recipe"
    ]
  ],
  "rewards": {
    "recipes": [
      "taloi:sermium_core"
    ]
  }
}